odoo/addons/l10n_ro_nondeductible_vat/README.rst
odoo/addons/l10n_ro_nondeductible_vat/__init__.py
odoo/addons/l10n_ro_nondeductible_vat/__manifest__.py
odoo/addons/l10n_ro_nondeductible_vat/models/__init__.py
odoo/addons/l10n_ro_nondeductible_vat/models/account_account.py
odoo/addons/l10n_ro_nondeductible_vat/models/account_move.py
odoo/addons/l10n_ro_nondeductible_vat/models/account_partial_reconcile.py
odoo/addons/l10n_ro_nondeductible_vat/models/account_tax.py
odoo/addons/l10n_ro_nondeductible_vat/models/stock_inventory_line.py
odoo/addons/l10n_ro_nondeductible_vat/models/stock_move.py
odoo/addons/l10n_ro_nondeductible_vat/readme/CONTRIBUTORS.rst
odoo/addons/l10n_ro_nondeductible_vat/readme/DESCRIPTION.rst
odoo/addons/l10n_ro_nondeductible_vat/readme/INSTALL.rst
odoo/addons/l10n_ro_nondeductible_vat/readme/USAGE.rst
odoo/addons/l10n_ro_nondeductible_vat/static/description/icon.png
odoo/addons/l10n_ro_nondeductible_vat/static/description/index.html
odoo/addons/l10n_ro_nondeductible_vat/tests/__init__.py
odoo/addons/l10n_ro_nondeductible_vat/tests/common.py
odoo/addons/l10n_ro_nondeductible_vat/tests/test_consum.py
odoo/addons/l10n_ro_nondeductible_vat/tests/test_inventory.py
odoo/addons/l10n_ro_nondeductible_vat/tests/test_invoice.py
odoo/addons/l10n_ro_nondeductible_vat/views/account_account_view.xml
odoo/addons/l10n_ro_nondeductible_vat/views/account_tax_view.xml
odoo/addons/l10n_ro_nondeductible_vat/views/stock_inventory_line_view.xml
odoo/addons/l10n_ro_nondeductible_vat/views/stock_picking_view.xml
odoo14_addon_l10n_ro_nondeductible_vat-14.0.1.3.0.dist-info/METADATA
odoo14_addon_l10n_ro_nondeductible_vat-14.0.1.3.0.dist-info/WHEEL
odoo14_addon_l10n_ro_nondeductible_vat-14.0.1.3.0.dist-info/top_level.txt
odoo14_addon_l10n_ro_nondeductible_vat-14.0.1.3.0.dist-info/RECORD
