Metadata-Version: 2.1
Name: odoo14-addon-l10n-ro-nondeductible-vat
Version: 14.0.1.3.0
Summary: Romania - Nondeductible VAT
Home-page: https://github.com/OCA/l10n-romania
Author: Dakai Soft SRL,NextERP Romania,Odoo Community Association (OCA)
Author-email: support@odoo-community.org
License: AGPL-3
Platform: UNKNOWN
Classifier: Programming Language :: Python
Classifier: Framework :: Odoo
Classifier: Framework :: Odoo :: 14.0
Classifier: License :: OSI Approved :: GNU Affero General Public License v3
Classifier: Development Status :: 6 - Mature
Requires-Python: >=3.6
Requires-Dist: odoo14-addon-l10n-ro-stock-account
Requires-Dist: odoo14-addon-l10n-ro-vat-on-payment
Requires-Dist: odoo (<14.1dev,>=14.0a)
